statpy/__init__.py
statpy/pdf_stat.py
stat_py_ryabov-1.2.0.dist-info/METADATA
stat_py_ryabov-1.2.0.dist-info/WHEEL
stat_py_ryabov-1.2.0.dist-info/top_level.txt
stat_py_ryabov-1.2.0.dist-info/RECORD
